mlffbrew/__init__.py
mlffbrew/_version.py
mlffbrew/dataclasses.py
mlffbrew/decorator.py
mlffbrew/slurm.py
mlffbrew/space.py
mlffbrew/typing.py
mlffbrew/programs/__init__.py
mlffbrew/programs/scripter.py
mlffbrew/programs/cp2k/__init__.py
mlffbrew/programs/cp2k/_static.py
mlffbrew/programs/cp2k/builder.py
mlffbrew/programs/cp2k/opener.py
mlffbrew/programs/cp2k/scripter.py
mlffbrew/programs/lammps/__init__.py
mlffbrew/programs/lammps/_static.py
mlffbrew/programs/lammps/builder.py
mlffbrew/programs/lammps/opener.py
mlffbrew/programs/lammps/scripter.py
mlffbrew/unit/__init__.py
mlffbrew/unit/_mutliplier.py
mlffbrew/unit/style.py
mlffbrew-0.0.1.dist-info/LICENSE
mlffbrew-0.0.1.dist-info/METADATA
mlffbrew-0.0.1.dist-info/WHEEL
mlffbrew-0.0.1.dist-info/top_level.txt
mlffbrew-0.0.1.dist-info/RECORD
